<?xml version="1.0" encoding="UTF-8"?>
<Defs>
	
	<ThingDef ParentName="OutlandFurnitureBase">
		<defName>Outland_Hokora</defName>
		<label>hokora</label>
		<description>A compact shrine building.</description>
		<category>Building</category>
		<thingClass>Building</thingClass>
		<graphicData>
			<texPath>Outland/Eastborn/Buildings/Hokora</texPath>
			<graphicClass>Graphic_Single</graphicClass>
			<shaderType>CutoutComplex</shaderType>
			<drawRotated>false</drawRotated>
			<drawSize>(4, 4)</drawSize>
            <drawOffset>(0.0, 0.0, 0.0)</drawOffset>
		</graphicData>
		<size>(2, 2)</size>
		<uiIconScale>0.8</uiIconScale>
		<rotatable>true</rotatable>
		<altitudeLayer>Building</altitudeLayer>
		<pathCost>500</pathCost>
		<passability>PassThroughOnly</passability>
		<tickerType>Normal</tickerType>
		<fillPercent>0.9</fillPercent>
		<leaveResourcesWhenKilled>true</leaveResourcesWhenKilled>
		<defaultPlacingRot>South</defaultPlacingRot>
		<statBases>
			<MaxHitPoints>400</MaxHitPoints>
			<WorkToBuild>250</WorkToBuild>
			<Flammability>0</Flammability>
			<Mass>4</Mass>
			<Beauty>10</Beauty>
		</statBases>
		<building>
			<isEdifice>false</isEdifice>
		</building>
		<costList>
			<WoodLog>50</WoodLog>
		</costList>
		<costStuffCount>120</costStuffCount>
		<stuffCategories>
			<li>Stony</li>
		</stuffCategories>
		<researchPrerequisites>
			<li>Outland_EastbornDeco</li>
		</researchPrerequisites>
		<designationCategory>Outland_OutlandDeco</designationCategory>
	</ThingDef>

</Defs>